Metadata-Version: 1.0
Name: esptester
Version: 0.0
Summary: My first test module
Home-page: UNKNOWN
Author: UNKNOWN
Author-email: igorkorobigor@gmail.com
License: UNKNOWN
Platform: UNKNOWN
